meilisearch_mcp/__init__.py
meilisearch_mcp/__main__.py
meilisearch_mcp/__version__.py
meilisearch_mcp/chat.py
meilisearch_mcp/client.py
meilisearch_mcp/documents.py
meilisearch_mcp/indexes.py
meilisearch_mcp/keys.py
meilisearch_mcp/logging.py
meilisearch_mcp/monitoring.py
meilisearch_mcp/server.py
meilisearch_mcp/settings.py
meilisearch_mcp/tasks.py
mseep_meilisearch_mcp-0.6.1.dist-info/licenses/LICENSE
mseep_meilisearch_mcp-0.6.1.dist-info/METADATA
mseep_meilisearch_mcp-0.6.1.dist-info/WHEEL
mseep_meilisearch_mcp-0.6.1.dist-info/entry_points.txt
mseep_meilisearch_mcp-0.6.1.dist-info/top_level.txt
mseep_meilisearch_mcp-0.6.1.dist-info/RECORD
